src/__init__.py
src/_version.py
src/mcp.py
thirdweb_mcp-0.1.24.dist-info/METADATA
thirdweb_mcp-0.1.24.dist-info/WHEEL
thirdweb_mcp-0.1.24.dist-info/entry_points.txt
thirdweb_mcp-0.1.24.dist-info/licenses/LICENSE
thirdweb_mcp-0.1.24.dist-info/RECORD
