Metadata-Version: 2.4
Name: thirdweb-mcp
Version: 0.1.24
Summary: thirdweb MCP
Author-email: thirdweb <support@thirdweb.com>
License-Expression: Apache-2.0
License-File: LICENSE
Requires-Python: ~=3.10
Requires-Dist: click<9,>=8.1.8
Requires-Dist: mcp<2,>=1.3.0
Requires-Dist: thirdweb-ai[mcp]==0.1.24
